{"contributors": null, "coordinates": {"coordinates": [-74.0064, 40.7142], "type": "Point"}, "created_at": "Sun Jan 26 21:20:43 +0000 2020", "entities": {"hashtags": [], "symbols": [], "urls": [{"display_url": "twitter.com/i/web/status/1\u2026", "expanded_url": "https://twitter.com/i/web/status/1221543511977353217", "indices": [117, 140], "url": "https://t.co/kQhNRZMa2m"}], "user_mentions": []}, "favorite_count": 0, "favorited": false, "geo": {"coordinates": [40.7142, -74.0064], "type": "Point"}, "id": 1221543511977353217, "id_str": "1221543511977353217", "in_reply_to_screen_name": null, "in_reply_to_status_id": null, "in_reply_to_status_id_str": null, "in_reply_to_user_id": null, "in_reply_to_user_id_str": null, "is_quote_status": false, "lang": "en", "metadata": {"iso_language_code": "en", "result_type": "recent"}, "place": {"attributes": {}, "bounding_box": {"coordinates": [[[-74.026675, 40.683935], [-73.910408, 40.683935], [-73.910408, 40.877483], [-74.026675, 40.877483]]], "type": "Polygon"}, "contained_within": [], "country": "United States", "country_code": "US", "full_name": "Manhattan, NY", "id": "01a9a39529b27f36", "name": "Manhattan", "place_type": "city", "url": "https://api.twitter.com/1.1/geo/id/01a9a39529b27f36.json"}, "possibly_sensitive": false, "retweet_count": 0, "retweeted": false, "source": "<a href=\"http://instagram.com\" rel=\"nofollow\">Instagram</a>", "text": "NBA champion Kobe Bryant\u00a0perished tragically in a helicopter crash\u00a0in Calabasas, California, on Sunday afternoon. T\u2026 https://t.co/kQhNRZMa2m", "truncated": true, "user": {"contributors_enabled": false, "created_at": "Fri Aug 12 19:32:56 +0000 2011", "default_profile": false, "default_profile_image": false, "description": "Owner/Creator, RAW Curves Media, LLC.\n#rawcurvesmedia #curvypreneur", "entities": {"description": {"urls": []}, "url": {"urls": [{"display_url": "rawcurves.media", "expanded_url": "http://www.rawcurves.media", "indices": [0, 23], "url": "https://t.co/z5mXTOTb6T"}]}}, "favourites_count": 1259, "follow_request_sent": null, "followers_count": 130, "following": null, "friends_count": 823, "geo_enabled": true, "has_extended_profile": true, "id": 353872802, "id_str": "353872802", "is_translation_enabled": false, "is_translator": false, "lang": null, "listed_count": 15, "location": "Brooklyn, NY", "name": "TAWaiters85", "notifications": null, "profile_background_color": "C0DEED", "profile_background_image_url": "http://abs.twimg.com/images/themes/theme1/bg.png", "profile_background_image_url_https": "https://abs.twimg.com/images/themes/theme1/bg.png", "profile_background_tile": true, "profile_banner_url": "https://pbs.twimg.com/profile_banners/353872802/1541732177", "profile_image_url": "http://pbs.twimg.com/profile_images/1060727883717582848/OQb27u5C_normal.jpg", "profile_image_url_https": "https://pbs.twimg.com/profile_images/1060727883717582848/OQb27u5C_normal.jpg", "profile_link_color": "1B95E0", "profile_sidebar_border_color": "000000", "profile_sidebar_fill_color": "DDEEF6", "profile_text_color": "333333", "profile_use_background_image": true, "protected": false, "screen_name": "RAWCurvesMedia", "statuses_count": 34265, "time_zone": null, "translator_type": "none", "url": "https://t.co/z5mXTOTb6T", "utc_offset": null, "verified": false}}
{"contributors": null, "coordinates": null, "created_at": "Sun Jan 26 21:20:33 +0000 2020", "entities": {"hashtags": [], "symbols": [], "urls": [{"display_url": "twitter.com/i/web/status/1\u2026", "expanded_url": "https://twitter.com/i/web/status/1221543471347007488", "indices": [117, 140], "url": "https://t.co/ecQbwM4XeU"}], "user_mentions": []}, "favorite_count": 2, "favorited": false, "geo": null, "id": 1221543471347007488, "id_str": "1221543471347007488", "in_reply_to_screen_name": null, "in_reply_to_status_id": null, "in_reply_to_status_id_str": null, "in_reply_to_user_id": null, "in_reply_to_user_id_str": null, "is_quote_status": true, "lang": "en", "metadata": {"iso_language_code": "en", "result_type": "recent"}, "place": {"attributes": {}, "bounding_box": {"coordinates": [[[-90.6921396, 41.475836], [-90.5027437, 41.475836], [-90.5027437, 41.6000496], [-90.6921396, 41.6000496]]], "type": "Polygon"}, "contained_within": [], "country": "United States", "country_code": "US", "full_name": "Davenport, IA", "id": "9c1c0a45346f5837", "name": "Davenport", "place_type": "city", "url": "https://api.twitter.com/1.1/geo/id/9c1c0a45346f5837.json"}, "possibly_sensitive": false, "quoted_status": {"contributors": null, "coordinates": null, "created_at": "Sun Jan 26 21:03:31 +0000 2020", "entities": {"hashtags": [], "symbols": [], "urls": [{"display_url": "twitter.com/i/web/status/1\u2026", "expanded_url": "https://twitter.com/i/web/status/1221539186156720130", "indices": [117, 140], "url": "https://t.co/g667s2ySUO"}], "user_mentions": [{"id": 1104241939157680128, "id_str": "1104241939157680128", "indices": [16, 31], "name": "Anna Hadahiil\u012f\u0301 Y\u00e1zh\u00ed \ud83e\udde2", "screen_name": "HadahiiliYazhi"}]}, "favorite_count": 7, "favorited": false, "geo": null, "id": 1221539186156720130, "id_str": "1221539186156720130", "in_reply_to_screen_name": null, "in_reply_to_status_id": null, "in_reply_to_status_id_str": null, "in_reply_to_user_id": null, "in_reply_to_user_id_str": null, "is_quote_status": false, "lang": "en", "metadata": {"iso_language_code": "en", "result_type": "recent"}, "place": null, "possibly_sensitive": false, "retweet_count": 0, "retweeted": false, "source": "<a href=\"http://twitter.com/download/iphone\" rel=\"nofollow\">Twitter for iPhone</a>", "text": "A sneak peak at @HadahiiliYazhi\u2019s tattoo \ud83d\ude0d\ud83d\ude0d. We will have to come back later to get it due to the detail in the des\u2026 https://t.co/g667s2ySUO", "truncated": true, "user": {"contributors_enabled": false, "created_at": "Tue May 07 05:00:49 +0000 2013", "default_profile": true, "default_profile_image": false, "description": "Designer with an insatiable desire to create. Metropolitan commuter. lover of politics. tech fanatic. proud millennial", "entities": {"description": {"urls": []}}, "favourites_count": 6139, "follow_request_sent": null, "followers_count": 4606, "following": null, "friends_count": 1395, "geo_enabled": true, "has_extended_profile": false, "id": 1409435996, "id_str": "1409435996", "is_translation_enabled": false, "is_translator": false, "lang": null, "listed_count": 32, "location": "New York City ", "name": "Katy Kinsey \ud83e\udde27\ufe0f\u20e3", "notifications": null, "profile_background_color": "C0DEED", "profile_background_image_url": "http://abs.twimg.com/images/themes/theme1/bg.png", "profile_background_image_url_https": "https://abs.twimg.com/images/themes/theme1/bg.png", "profile_background_tile": false, "profile_banner_url": "https://pbs.twimg.com/profile_banners/1409435996/1569356812", "profile_image_url": "http://pbs.twimg.com/profile_images/978321761413541889/Ah8QDydL_normal.jpg", "profile_image_url_https": "https://pbs.twimg.com/profile_images/978321761413541889/Ah8QDydL_normal.jpg", "profile_link_color": "1DA1F2", "profile_sidebar_border_color": "C0DEED", "profile_sidebar_fill_color": "DDEEF6", "profile_text_color": "333333", "profile_use_background_image": true, "protected": false, "screen_name": "Kinsey_ka", "statuses_count": 3303, "time_zone": null, "translator_type": "none", "url": null, "utc_offset": null, "verified": false}}, "quoted_status_id": 1221539186156720130, "quoted_status_id_str": "1221539186156720130", "retweet_count": 0, "retweeted": false, "source": "<a href=\"http://twitter.com/download/iphone\" rel=\"nofollow\">Twitter for iPhone</a>", "text": "\ud83d\ude02 I can\u2019t wait to get this. Pikachu will be shooting lasers out his eyes and it will say I Have The Data. It will b\u2026 https://t.co/ecQbwM4XeU", "truncated": true, "user": {"contributors_enabled": false, "created_at": "Sat Mar 09 04:46:08 +0000 2019", "default_profile": true, "default_profile_image": false, "description": "Navajo Nation (Naakai Dine\u2019\u00e9/Bilag\u00e1ana), Multidisciplinary Artist & Musician, Beadwork, #YangGang", "entities": {"description": {"urls": []}, "url": {"urls": [{"display_url": "etsy.com/shop/naataanii\u2026", "expanded_url": "http://www.etsy.com/shop/naataaniiyang", "indices": [0, 23], "url": "https://t.co/EhoiTUNdzv"}]}}, "favourites_count": 14390, "follow_request_sent": null, "followers_count": 4194, "following": null, "friends_count": 3519, "geo_enabled": true, "has_extended_profile": false, "id": 1104241939157680128, "id_str": "1104241939157680128", "is_translation_enabled": false, "is_translator": false, "lang": null, "listed_count": 22, "location": "Ti'tsa-pa, Utah", "name": "Anna Hadahiil\u012f\u0301 Y\u00e1zh\u00ed \ud83e\udde2", "notifications": null, "profile_background_color": "F5F8FA", "profile_background_image_url": null, "profile_background_image_url_https": null, "profile_background_tile": false, "profile_banner_url": "https://pbs.twimg.com/profile_banners/1104241939157680128/1576099075", "profile_image_url": "http://pbs.twimg.com/profile_images/1217542828353622017/Rdt0jBH5_normal.jpg", "profile_image_url_https": "https://pbs.twimg.com/profile_images/1217542828353622017/Rdt0jBH5_normal.jpg", "profile_link_color": "1DA1F2", "profile_sidebar_border_color": "C0DEED", "profile_sidebar_fill_color": "DDEEF6", "profile_text_color": "333333", "profile_use_background_image": true, "protected": false, "screen_name": "HadahiiliYazhi", "statuses_count": 5597, "time_zone": null, "translator_type": "none", "url": "https://t.co/EhoiTUNdzv", "utc_offset": null, "verified": false}}
{"contributors": null, "coordinates": null, "created_at": "Sun Jan 26 21:18:42 +0000 2020", "entities": {"hashtags": [], "symbols": [], "urls": [{"display_url": "twitter.com/breaking911/st\u2026", "expanded_url": "https://twitter.com/breaking911/status/1221537639670734856", "indices": [92, 115], "url": "https://t.co/WofFDOpApt"}], "user_mentions": []}, "favorite_count": 0, "favorited": false, "geo": null, "id": 1221543006324559872, "id_str": "1221543006324559872", "in_reply_to_screen_name": null, "in_reply_to_status_id": null, "in_reply_to_status_id_str": null, "in_reply_to_user_id": null, "in_reply_to_user_id_str": null, "is_quote_status": true, "lang": "en", "metadata": {"iso_language_code": "en", "result_type": "recent"}, "place": {"attributes": {}, "bounding_box": {"coordinates": [[[-75.280284, 39.871811], [-74.955712, 39.871811], [-74.955712, 40.13792], [-75.280284, 40.13792]]], "type": "Polygon"}, "contained_within": [], "country": "United States", "country_code": "US", "full_name": "Philadelphia, PA", "id": "e4a0d228eb6be76b", "name": "Philadelphia", "place_type": "city", "url": "https://api.twitter.com/1.1/geo/id/e4a0d228eb6be76b.json"}, "possibly_sensitive": false, "quoted_status": {"contributors": null, "coordinates": null, "created_at": "Sun Jan 26 20:57:23 +0000 2020", "entities": {"hashtags": [], "symbols": [], "urls": [], "user_mentions": []}, "favorite_count": 8387, "favorited": false, "geo": null, "id": 1221537639670734856, "id_str": "1221537639670734856", "in_reply_to_screen_name": null, "in_reply_to_status_id": null, "in_reply_to_status_id_str": null, "in_reply_to_user_id": null, "in_reply_to_user_id_str": null, "is_quote_status": false, "lang": "en", "metadata": {"iso_language_code": "en", "result_type": "recent"}, "place": null, "retweet_count": 6497, "retweeted": false, "source": "<a href=\"http://twitter.com/download/iphone\" rel=\"nofollow\">Twitter for iPhone</a>", "text": "BREAKING: 3 rockets make direct hit on the US embassy in Baghdad - AFP", "truncated": false, "user": {"contributors_enabled": false, "created_at": "Sun Sep 18 16:36:06 +0000 2011", "default_profile": false, "default_profile_image": false, "description": "Breaking news in live time for over 8 years. Now 430K strong! Follow @Breaking911 and visit https://t.co/RWBI1f2gDw to stay updated", "entities": {"description": {"urls": [{"display_url": "Breaking911.com", "expanded_url": "http://Breaking911.com", "indices": [92, 115], "url": "https://t.co/RWBI1f2gDw"}]}, "url": {"urls": [{"display_url": "Breaking911.com", "expanded_url": "http://Breaking911.com", "indices": [0, 23], "url": "https://t.co/RWBI1f2gDw"}]}}, "favourites_count": 2, "follow_request_sent": null, "followers_count": 441823, "following": null, "friends_count": 0, "geo_enabled": false, "has_extended_profile": false, "id": 375721095, "id_str": "375721095", "is_translation_enabled": false, "is_translator": false, "lang": null, "listed_count": 5194, "location": "Nashville", "name": "Breaking911", "notifications": null, "profile_background_color": "C0DEED", "profile_background_image_url": "http://abs.twimg.com/images/themes/theme1/bg.png", "profile_background_image_url_https": "https://abs.twimg.com/images/themes/theme1/bg.png", "profile_background_tile": false, "profile_banner_url": "https://pbs.twimg.com/profile_banners/375721095/1496844300", "profile_image_url": "http://pbs.twimg.com/profile_images/619546088995979264/KuG27bBK_normal.jpg", "profile_image_url_https": "https://pbs.twimg.com/profile_images/619546088995979264/KuG27bBK_normal.jpg", "profile_link_color": "0084B4", "profile_sidebar_border_color": "FFFFFF", "profile_sidebar_fill_color": "DDEEF6", "profile_text_color": "333333", "profile_use_background_image": true, "protected": false, "screen_name": "Breaking911", "statuses_count": 187, "time_zone": null, "translator_type": "none", "url": "https://t.co/RWBI1f2gDw", "utc_offset": null, "verified": false}}, "quoted_status_id": 1221537639670734856, "quoted_status_id_str": "1221537639670734856", "retweet_count": 0, "retweeted": false, "source": "<a href=\"http://twitter.com/download/iphone\" rel=\"nofollow\">Twitter for iPhone</a>", "text": "This the wrong time for niggas to be shooting rockets man the country in mourning right now https://t.co/WofFDOpApt", "truncated": false, "user": {"contributors_enabled": false, "created_at": "Thu May 13 20:28:56 +0000 2010", "default_profile": false, "default_profile_image": false, "description": "", "entities": {"description": {"urls": []}, "url": {"urls": [{"display_url": "gtfdrtghjjj.com", "expanded_url": "http://www.gtfdrtghjjj.com", "indices": [0, 23], "url": "https://t.co/cpkltKhZzv"}]}}, "favourites_count": 8761, "follow_request_sent": null, "followers_count": 4630, "following": null, "friends_count": 1438, "geo_enabled": true, "has_extended_profile": false, "id": 143562713, "id_str": "143562713", "is_translation_enabled": false, "is_translator": false, "lang": null, "listed_count": 51, "location": "", "name": "...", "notifications": null, "profile_background_color": "C0DEED", "profile_background_image_url": "http://abs.twimg.com/images/themes/theme1/bg.png", "profile_background_image_url_https": "https://abs.twimg.com/images/themes/theme1/bg.png", "profile_background_tile": false, "profile_banner_url": "https://pbs.twimg.com/profile_banners/143562713/1579640219", "profile_image_url": "http://pbs.twimg.com/profile_images/1219806740277006337/L40c-kb8_normal.jpg", "profile_image_url_https": "https://pbs.twimg.com/profile_images/1219806740277006337/L40c-kb8_normal.jpg", "profile_link_color": "0084B4", "profile_sidebar_border_color": "C0DEED", "profile_sidebar_fill_color": "DDEEF6", "profile_text_color": "333333", "profile_use_background_image": true, "protected": false, "screen_name": "Hunitproof", "statuses_count": 331195, "time_zone": null, "translator_type": "none", "url": "https://t.co/cpkltKhZzv", "utc_offset": null, "verified": false}}
{"contributors": null, "coordinates": null, "created_at": "Sun Jan 26 21:17:35 +0000 2020", "entities": {"hashtags": [], "symbols": [], "urls": [], "user_mentions": []}, "favorite_count": 12, "favorited": false, "geo": null, "id": 1221542724811227138, "id_str": "1221542724811227138", "in_reply_to_screen_name": null, "in_reply_to_status_id": null, "in_reply_to_status_id_str": null, "in_reply_to_user_id": null, "in_reply_to_user_id_str": null, "is_quote_status": false, "lang": "en", "metadata": {"iso_language_code": "en", "result_type": "recent"}, "place": {"attributes": {}, "bounding_box": {"coordinates": [[[-83.288056, 42.255085], [-82.91052, 42.255085], [-82.91052, 42.450488], [-83.288056, 42.450488]]], "type": "Polygon"}, "contained_within": [], "country": "United States", "country_code": "US", "full_name": "Detroit, MI", "id": "b463d3bd6064861b", "name": "Detroit", "place_type": "city", "url": "https://api.twitter.com/1.1/geo/id/b463d3bd6064861b.json"}, "retweet_count": 5, "retweeted": false, "source": "<a href=\"http://twitter.com/download/iphone\" rel=\"nofollow\">Twitter for iPhone</a>", "text": "Shooting a piece of paper into the trash can will never be the same...", "truncated": false, "user": {"contributors_enabled": false, "created_at": "Tue May 17 22:39:11 +0000 2011", "default_profile": false, "default_profile_image": false, "description": "Detroit @freep Neighborhood Reporter. Alderman of the Eastside. Detroit Griot. \u2018Writing for my life \u2018cause I'm scared of a day job.'", "entities": {"description": {"urls": []}}, "favourites_count": 2234, "follow_request_sent": null, "followers_count": 11971, "following": null, "friends_count": 2826, "geo_enabled": true, "has_extended_profile": true, "id": 300529264, "id_str": "300529264", "is_translation_enabled": false, "is_translator": false, "lang": null, "listed_count": 161, "location": "Eastside of Detroit", "name": "Branden Hunter \ud83c\udfc1", "notifications": null, "profile_background_color": "131516", "profile_background_image_url": "http://abs.twimg.com/images/themes/theme14/bg.gif", "profile_background_image_url_https": "https://abs.twimg.com/images/themes/theme14/bg.gif", "profile_background_tile": false, "profile_banner_url": "https://pbs.twimg.com/profile_banners/300529264/1545231210", "profile_image_url": "http://pbs.twimg.com/profile_images/1218623411527634944/K9giChfy_normal.jpg", "profile_image_url_https": "https://pbs.twimg.com/profile_images/1218623411527634944/K9giChfy_normal.jpg", "profile_link_color": "8A8987", "profile_sidebar_border_color": "EEEEEE", "profile_sidebar_fill_color": "EFEFEF", "profile_text_color": "000000", "profile_use_background_image": true, "protected": false, "screen_name": "JustCallmeBHunt", "statuses_count": 155855, "time_zone": null, "translator_type": "none", "url": null, "utc_offset": null, "verified": false}}
{"contributors": null, "coordinates": null, "created_at": "Sun Jan 26 21:17:31 +0000 2020", "entities": {"hashtags": [], "symbols": [], "urls": [], "user_mentions": []}, "favorite_count": 0, "favorited": false, "geo": null, "id": 1221542709485281287, "id_str": "1221542709485281287", "in_reply_to_screen_name": null, "in_reply_to_status_id": null, "in_reply_to_status_id_str": null, "in_reply_to_user_id": null, "in_reply_to_user_id_str": null, "is_quote_status": false, "lang": "en", "metadata": {"iso_language_code": "en", "result_type": "recent"}, "place": {"attributes": {}, "bounding_box": {"coordinates": [[[-83.831237, 42.899436], [-83.6199828, 42.899436], [-83.6199828, 43.089481], [-83.831237, 43.089481]]], "type": "Polygon"}, "contained_within": [], "country": "United States", "country_code": "US", "full_name": "Flint, MI", "id": "0138153149b79c7f", "name": "Flint", "place_type": "city", "url": "https://api.twitter.com/1.1/geo/id/0138153149b79c7f.json"}, "retweet_count": 0, "retweeted": false, "source": "<a href=\"http://twitter.com/download/iphone\" rel=\"nofollow\">Twitter for iPhone</a>", "text": "I\u2019ll still be in the driveway shooting yelling KOBEEEEEEE. RIP \ud83d\udc0d", "truncated": false, "user": {"contributors_enabled": false, "created_at": "Mon Dec 06 23:44:55 +0000 2010", "default_profile": false, "default_profile_image": false, "description": "Driver of the #7 Wing Sprintcar with the Great Lakes Super Sprints (@GLSuperSprints)", "entities": {"description": {"urls": []}}, "favourites_count": 1499, "follow_request_sent": null, "followers_count": 1045, "following": null, "friends_count": 117, "geo_enabled": true, "has_extended_profile": true, "id": 223650301, "id_str": "223650301", "is_translation_enabled": false, "is_translator": false, "lang": null, "listed_count": 17, "location": "Bray Road Bullet", "name": "Trevor Berry", "notifications": null, "profile_background_color": "131516", "profile_background_image_url": "http://abs.twimg.com/images/themes/theme14/bg.gif", "profile_background_image_url_https": "https://abs.twimg.com/images/themes/theme14/bg.gif", "profile_background_tile": true, "profile_banner_url": "https://pbs.twimg.com/profile_banners/223650301/1560825515", "profile_image_url": "http://pbs.twimg.com/profile_images/1013772974674063360/CugV1uug_normal.jpg", "profile_image_url_https": "https://pbs.twimg.com/profile_images/1013772974674063360/CugV1uug_normal.jpg", "profile_link_color": "009999", "profile_sidebar_border_color": "EEEEEE", "profile_sidebar_fill_color": "EFEFEF", "profile_text_color": "333333", "profile_use_background_image": true, "protected": false, "screen_name": "Trevor_Berry", "statuses_count": 6865, "time_zone": null, "translator_type": "none", "url": null, "utc_offset": null, "verified": false}}
{"contributors": null, "coordinates": null, "created_at": "Sun Jan 26 21:16:44 +0000 2020", "entities": {"hashtags": [{"indices": [83, 88], "text": "Kobe"}], "symbols": [], "urls": [], "user_mentions": []}, "favorite_count": 0, "favorited": false, "geo": null, "id": 1221542511044374528, "id_str": "1221542511044374528", "in_reply_to_screen_name": null, "in_reply_to_status_id": null, "in_reply_to_status_id_str": null, "in_reply_to_user_id": null, "in_reply_to_user_id_str": null, "is_quote_status": false, "lang": "en", "metadata": {"iso_language_code": "en", "result_type": "recent"}, "place": {"attributes": {}, "bounding_box": {"coordinates": [[[-75.280284, 39.871811], [-74.955712, 39.871811], [-74.955712, 40.13792], [-75.280284, 40.13792]]], "type": "Polygon"}, "contained_within": [], "country": "United States", "country_code": "US", "full_name": "Philadelphia, PA", "id": "e4a0d228eb6be76b", "name": "Philadelphia", "place_type": "city", "url": "https://api.twitter.com/1.1/geo/id/e4a0d228eb6be76b.json"}, "retweet_count": 0, "retweeted": false, "source": "<a href=\"http://twitter.com/download/iphone\" rel=\"nofollow\">Twitter for iPhone</a>", "text": "And just like that, shooting paper balls into the trash can won\u2019t ever be the same #Kobe", "truncated": false, "user": {"contributors_enabled": false, "created_at": "Mon Aug 10 13:42:38 +0000 2009", "default_profile": false, "default_profile_image": false, "description": "@templeuniv MPH Candidate\ud83c\udf52@Penn Research Coordinator-Addiction Medicine \ud83d\udc9c harm reduction, music and photography \u2728opinions are my own \ud83d\udc81\ud83c\udffc\u200d\u2640\ufe0f", "entities": {"description": {"urls": []}}, "favourites_count": 5670, "follow_request_sent": null, "followers_count": 641, "following": null, "friends_count": 1461, "geo_enabled": true, "has_extended_profile": false, "id": 64405670, "id_str": "64405670", "is_translation_enabled": false, "is_translator": false, "lang": null, "listed_count": 15, "location": "philadelphia, pa", "name": "brittany salerno", "notifications": null, "profile_background_color": "B2DFDA", "profile_background_image_url": "http://abs.twimg.com/images/themes/theme13/bg.gif", "profile_background_image_url_https": "https://abs.twimg.com/images/themes/theme13/bg.gif", "profile_background_tile": true, "profile_banner_url": "https://pbs.twimg.com/profile_banners/64405670/1560475707", "profile_image_url": "http://pbs.twimg.com/profile_images/1214761577058058240/Rf6z_NbC_normal.jpg", "profile_image_url_https": "https://pbs.twimg.com/profile_images/1214761577058058240/Rf6z_NbC_normal.jpg", "profile_link_color": "93A644", "profile_sidebar_border_color": "FFFFFF", "profile_sidebar_fill_color": "FFFFFF", "profile_text_color": "333333", "profile_use_background_image": true, "protected": false, "screen_name": "_earth2brittany", "statuses_count": 9364, "time_zone": null, "translator_type": "none", "url": null, "utc_offset": null, "verified": false}}
{"contributors": null, "coordinates": null, "created_at": "Sun Jan 26 21:16:24 +0000 2020", "entities": {"hashtags": [], "symbols": [], "urls": [], "user_mentions": []}, "favorite_count": 0, "favorited": false, "geo": null, "id": 1221542425467817984, "id_str": "1221542425467817984", "in_reply_to_screen_name": null, "in_reply_to_status_id": null, "in_reply_to_status_id_str": null, "in_reply_to_user_id": null, "in_reply_to_user_id_str": null, "is_quote_status": false, "lang": "en", "metadata": {"iso_language_code": "en", "result_type": "recent"}, "place": {"attributes": {}, "bounding_box": {"coordinates": [[[-119.93251, 36.648905], [-119.632419, 36.648905], [-119.632419, 36.923179], [-119.93251, 36.923179]]], "type": "Polygon"}, "contained_within": [], "country": "United States", "country_code": "US", "full_name": "Fresno, CA", "id": "944c03c1d85ef480", "name": "Fresno", "place_type": "city", "url": "https://api.twitter.com/1.1/geo/id/944c03c1d85ef480.json"}, "retweet_count": 0, "retweeted": false, "source": "<a href=\"http://twitter.com/download/iphone\" rel=\"nofollow\">Twitter for iPhone</a>", "text": "shooting something into the trash yelling Kobe will never be the same \ud83d\ude1e", "truncated": false, "user": {"contributors_enabled": false, "created_at": "Sun Oct 16 16:44:27 +0000 2011", "default_profile": true, "default_profile_image": false, "description": "", "entities": {"description": {"urls": []}}, "favourites_count": 1288, "follow_request_sent": null, "followers_count": 145, "following": null, "friends_count": 182, "geo_enabled": true, "has_extended_profile": true, "id": 392157713, "id_str": "392157713", "is_translation_enabled": false, "is_translator": false, "lang": null, "listed_count": 1, "location": "Fresno, CA", "name": "Ivan Morales", "notifications": null, "profile_background_color": "C0DEED", "profile_background_image_url": "http://abs.twimg.com/images/themes/theme1/bg.png", "profile_background_image_url_https": "https://abs.twimg.com/images/themes/theme1/bg.png", "profile_background_tile": false, "profile_banner_url": "https://pbs.twimg.com/profile_banners/392157713/1578632898", "profile_image_url": "http://pbs.twimg.com/profile_images/1196311555018674176/UPnVeMpt_normal.jpg", "profile_image_url_https": "https://pbs.twimg.com/profile_images/1196311555018674176/UPnVeMpt_normal.jpg", "profile_link_color": "1DA1F2", "profile_sidebar_border_color": "C0DEED", "profile_sidebar_fill_color": "DDEEF6", "profile_text_color": "333333", "profile_use_background_image": true, "protected": false, "screen_name": "ivanCFC559", "statuses_count": 507, "time_zone": null, "translator_type": "none", "url": null, "utc_offset": null, "verified": false}}
{"contributors": null, "coordinates": null, "created_at": "Sun Jan 26 21:16:03 +0000 2020", "entities": {"hashtags": [], "symbols": [], "urls": [], "user_mentions": []}, "favorite_count": 0, "favorited": false, "geo": null, "id": 1221542337681199104, "id_str": "1221542337681199104", "in_reply_to_screen_name": null, "in_reply_to_status_id": null, "in_reply_to_status_id_str": null, "in_reply_to_user_id": null, "in_reply_to_user_id_str": null, "is_quote_status": false, "lang": "en", "metadata": {"iso_language_code": "en", "result_type": "recent"}, "place": {"attributes": {}, "bounding_box": {"coordinates": [[[-97.028288, 32.541286], [-96.891039, 32.541286], [-96.891039, 32.649242], [-97.028288, 32.649242]]], "type": "Polygon"}, "contained_within": [], "country": "United States", "country_code": "US", "full_name": "Cedar Hill, TX", "id": "4233ec320eb73634", "name": "Cedar Hill", "place_type": "city", "url": "https://api.twitter.com/1.1/geo/id/4233ec320eb73634.json"}, "retweet_count": 0, "retweeted": false, "source": "<a href=\"http://twitter.com/download/iphone\" rel=\"nofollow\">Twitter for iPhone</a>", "text": "kobe dead and they playin 2 hand touch in the Pro Bowl mfs shooting missles at our asses", "truncated": false, "user": {"contributors_enabled": false, "created_at": "Wed Jun 12 01:24:15 +0000 2013", "default_profile": true, "default_profile_image": false, "description": "94 \ud83e\uddda\u200d\u2640\ufe0f", "entities": {"description": {"urls": []}}, "favourites_count": 48431, "follow_request_sent": null, "followers_count": 354, "following": null, "friends_count": 177, "geo_enabled": true, "has_extended_profile": true, "id": 1508066341, "id_str": "1508066341", "is_translation_enabled": false, "is_translator": false, "lang": null, "listed_count": 2, "location": "Cedar Hill, TX", "name": "drew", "notifications": null, "profile_background_color": "C0DEED", "profile_background_image_url": "http://abs.twimg.com/images/themes/theme1/bg.png", "profile_background_image_url_https": "https://abs.twimg.com/images/themes/theme1/bg.png", "profile_background_tile": false, "profile_banner_url": "https://pbs.twimg.com/profile_banners/1508066341/1579284282", "profile_image_url": "http://pbs.twimg.com/profile_images/1166575585533014016/JW81oCJC_normal.jpg", "profile_image_url_https": "https://pbs.twimg.com/profile_images/1166575585533014016/JW81oCJC_normal.jpg", "profile_link_color": "1DA1F2", "profile_sidebar_border_color": "C0DEED", "profile_sidebar_fill_color": "DDEEF6", "profile_text_color": "333333", "profile_use_background_image": true, "protected": false, "screen_name": "yachtboycoy", "statuses_count": 19426, "time_zone": null, "translator_type": "none", "url": null, "utc_offset": null, "verified": false}}
